causal_discovery/algos/notears.py
causal_discovery/scripts/display_network.py
causal_discovery/scripts/run_notears.py
causal_discovery/synthetic_dataset.py
causal_discovery/utils.py
causal_discovery-0.1.1.dist-info/LICENSE
causal_discovery-0.1.1.dist-info/WHEEL
causal_discovery-0.1.1.dist-info/METADATA
causal_discovery-0.1.1.dist-info/RECORD
