Metadata-Version: 2.1
Name: causal-discovery
Version: 0.1.1
Summary: 
Author: nutorbit
Author-email: nutorbitx@gmail.com
Requires-Python: >=3.8,<4.0
Classifier: Programming Language :: Python :: 3
Classifier: Programming Language :: Python :: 3.8
Classifier: Programming Language :: Python :: 3.9
Classifier: Programming Language :: Python :: 3.10
Classifier: Programming Language :: Python :: 3.11
Requires-Dist: dm-haiku (>=0.0.9,<0.0.10)
Requires-Dist: jax (>=0.4.1,<0.5.0)
Requires-Dist: jaxlib (>=0.4.1,<0.5.0)
Requires-Dist: matplotlib (>=3.6.2,<4.0.0)
Requires-Dist: networkx (>=2.8.8,<3.0.0)
Requires-Dist: optax (>=0.1.4,<0.2.0)
Requires-Dist: pyvis (>=0.3.1,<0.4.0)
Requires-Dist: seaborn (>=0.12.1,<0.13.0)
Requires-Dist: tqdm (>=4.64.1,<5.0.0)
